toproxypdf/__init__.py
toproxypdf/__main__.py
toproxypdf/funcs/__init__.py
toproxypdf-0.1.5.dist-info/LICENSE
toproxypdf-0.1.5.dist-info/METADATA
toproxypdf-0.1.5.dist-info/WHEEL
toproxypdf-0.1.5.dist-info/entry_points.txt
toproxypdf-0.1.5.dist-info/top_level.txt
toproxypdf-0.1.5.dist-info/RECORD
