Metadata-Version: 2.1
Name: toproxypdf
Version: 0.1.5
Summary: converts proxy images into pdf
Home-page: https://github.com/feimaomiao/toproxypdf
Author: Matthew Lam
Author-email: lcpmatthew@gmail.com
Project-URL: Bug Tracker, https://github.com/feimaomiao/toproxypdf/issues
Classifier: Programming Language :: Python :: 3
Classifier: License :: OSI Approved :: MIT License
Classifier: Operating System :: OS Independent
Requires-Python: >=3.6
License-File: LICENSE
Requires-Dist: colorama (>=0.4.4)
Requires-Dist: Pillow (>=9.1.1)
Requires-Dist: tqdm (>=4.64.0)
